pygomas/__init__.py
pygomas/cli.py
pygomas/config.py
pygomas/manager.py
pygomas/map.py
pygomas/ontology.py
pygomas/server.py
pygomas/stats.py
pygomas/ASL/bdifieldop.asl
pygomas/ASL/bdimedic.asl
pygomas/ASL/bdisoldier.asl
pygomas/agents/__init__.py
pygomas/agents/agent.py
pygomas/agents/bdifieldop.py
pygomas/agents/bdimedic.py
pygomas/agents/bdisoldier.py
pygomas/agents/bditroop.py
pygomas/agents/service.py
pygomas/algorithms/__init__.py
pygomas/algorithms/a_star.py
pygomas/algorithms/jps.py
pygomas/assets/.DS_Store
pygomas/assets/ammopack.png
pygomas/assets/base1.png
pygomas/assets/base2.png
pygomas/assets/base3.png
pygomas/assets/base4.png
pygomas/assets/fieldops_allied1.png
pygomas/assets/fieldops_allied2.png
pygomas/assets/fieldops_allied3.png
pygomas/assets/fieldops_allied4.png
pygomas/assets/fieldops_allied5.png
pygomas/assets/fieldops_allied6.png
pygomas/assets/fieldops_allied7.png
pygomas/assets/fieldops_allied8.png
pygomas/assets/fieldops_axis1.png
pygomas/assets/fieldops_axis2.png
pygomas/assets/fieldops_axis3.png
pygomas/assets/fieldops_axis4.png
pygomas/assets/fieldops_axis5.png
pygomas/assets/fieldops_axis6.png
pygomas/assets/fieldops_axis7.png
pygomas/assets/fieldops_axis8.png
pygomas/assets/flag_1.png
pygomas/assets/flag_2.png
pygomas/assets/flag_3.png
pygomas/assets/flag_4.png
pygomas/assets/flag_5.png
pygomas/assets/flag_6.png
pygomas/assets/flag_7.png
pygomas/assets/flag_8.png
pygomas/assets/grass copia.jpg
pygomas/assets/grass.jpg
pygomas/assets/grass2.jpg
pygomas/assets/grave_allied1.png
pygomas/assets/grave_axis1.png
pygomas/assets/medic_allied1.png
pygomas/assets/medic_allied2.png
pygomas/assets/medic_allied3.png
pygomas/assets/medic_allied4.png
pygomas/assets/medic_allied5.png
pygomas/assets/medic_allied6.png
pygomas/assets/medic_allied7.png
pygomas/assets/medic_allied8.png
pygomas/assets/medic_axis1.png
pygomas/assets/medic_axis2.png
pygomas/assets/medic_axis3.png
pygomas/assets/medic_axis4.png
pygomas/assets/medic_axis5.png
pygomas-0.5.1.dist-info/AUTHORS.rst
pygomas-0.5.1.dist-info/LICENSE
pygomas-0.5.1.dist-info/METADATA
pygomas-0.5.1.dist-info/WHEEL
pygomas-0.5.1.dist-info/entry_points.txt
pygomas-0.5.1.dist-info/top_level.txt
pygomas-0.5.1.dist-info/RECORD
