Metadata-Version: 2.1
Name: pygomas
Version: 0.5.1
Summary: A Python 'capture the flag' Game Oriented Multiagent System.
Home-page: https://github.com/javipalanca/pygomas
Author: Sergio Frayle Pérez
Author-email: sfp932705@gmail.com
License: GNU General Public License v3
Keywords: pygomas
Platform: UNKNOWN
Classifier: Development Status :: 2 - Pre-Alpha
Classifier: Intended Audience :: Developers
Classifier: License :: OSI Approved :: GNU General Public License v3 (GPLv3)
Classifier: Natural Language :: English
Classifier: Programming Language :: Python :: 3
Classifier: Programming Language :: Python :: 3.6
Classifier: Programming Language :: Python :: 3.7
License-File: LICENSE
License-File: AUTHORS.rst
Requires-Dist: spade (==3.3.2)
Requires-Dist: spade-bdi (==0.3.1)
Requires-Dist: numpy (==1.26.2)
Requires-Dist: loguru (==0.2.5)
Requires-Dist: pqdict (==1.0.0)
Requires-Dist: click (==8.1.7)
Requires-Dist: pygame (==2.5.2)
Requires-Dist: msgpack (==1.0.7)
Requires-Dist: strenum (==0.4.15)
